setup.py
scripts/templeton
scripts/templeton.fcgi
scripts/templetond
templeton/__init__.py
templeton/events.py
templeton/handlers.py
templeton/middleware.py
templeton.egg-info/PKG-INFO
templeton.egg-info/SOURCES.txt
templeton.egg-info/dependency_links.txt
templeton.egg-info/not-zip-safe
templeton.egg-info/requires.txt
templeton.egg-info/top_level.txt