Metadata-Version: 1.0
Name: templeton
Version: 0.6.1
Summary: Minimal web framework for rapid development of web tools
Home-page: https://github.com/markrcote/templeton
Author: Mark Cote
Author-email: mcote@mozilla.com
License: MPL
Platform: UNKNOWN
